[
    {
        "title": "Past and current research",
        "recordedOn": "January 13th, 2014, Milano (IT)",
        "link": "//player.vimeo.com/video/98439511",
        "description": " Here is the talk I gave about my research interests in computer modeling and architecture, focusing on the lessons I've learnt along the way.",
        "languages": [ "spoken: italian", "slides: english" ]
    },
    {
        "title": "DAC 2012 University Booth",
        "recordedOn": "June 2012, San Francisco (US)",
        "link": "//www.youtube.com/embed/Ne6Y8Pg6MfY",
        "description": "The video we presented at the Design Automation Conference on June 2012."}

    ]
